hackerfeed-0.1.data/scripts/hfeed
hackerfeed-0.1.dist-info/DESCRIPTION.rst
hackerfeed-0.1.dist-info/METADATA
hackerfeed-0.1.dist-info/RECORD
hackerfeed-0.1.dist-info/WHEEL
hackerfeed-0.1.dist-info/metadata.json
hackerfeed-0.1.dist-info/top_level.txt
hfeedlib/__init__.py
hfeedlib/fetchlib.py
hfeedlib/hfeed_main.py
hfeedlib/utils.py
hfeedlib/parsing/__init__.py
hfeedlib/parsing/cli.py
hfeedlib/parsing/save.py
