Metadata-Version: 2.0
Name: hackerfeed
Version: 0.1
Summary: Read hackernews right from your terminal!
Home-page: https://github.com/pratyushprakash/HackerFeed
Author: Pratyush Prakash
Author-email: pratyushprakash@live.co.uk
License: MIT
Keywords: news hacker hackernews terminal
Platform: UNKNOWN
Requires-Dist: colorama
Requires-Dist: requests
